pytest_monkeytype/__init__.py
pytest_monkeytype/plugin.py
pytest_monkeytype-1.0.1.dist-info/DESCRIPTION.rst
pytest_monkeytype-1.0.1.dist-info/METADATA
pytest_monkeytype-1.0.1.dist-info/RECORD
pytest_monkeytype-1.0.1.dist-info/WHEEL
pytest_monkeytype-1.0.1.dist-info/entry_points.txt
pytest_monkeytype-1.0.1.dist-info/metadata.json
pytest_monkeytype-1.0.1.dist-info/top_level.txt
tests/__init__.py
tests/test_annotation.py
