Metadata-Version: 2.0
Name: pytest-monkeytype
Version: 1.0.1
Summary: pytest-monkeytype: Generate Monkeytype annotations from your pytest tests.
Home-page: UNKNOWN
Author: Marius van Niekerk
Author-email: marius.v.niekerk@gmail.com
License: MIT
Keywords: pytest py.test types annotations MonkeyType monkeytype pep484
Platform: UNKNOWN
Classifier: Development Status :: 4 - Beta
Classifier: Environment :: Console
Classifier: Intended Audience :: Developers
Classifier: Framework :: Pytest
Classifier: License :: OSI Approved :: MIT License
Classifier: Programming Language :: Python :: 3
Classifier: Programming Language :: Python :: 3.6
Classifier: Programming Language :: Python :: 3.7
Classifier: Topic :: Software Development
Classifier: Topic :: Software Development :: Testing
Requires-Python: >=3.6
Requires-Dist: MonkeyType (>=18.2.0)
Requires-Dist: pytest (>=3.2.0)
